<?xml version="1.0" encoding="us-ascii"?>
<Catalog>
    <CLight id="Tyrador">
        <ToDInfoArray index="0" AmbientColor="0.427451,0.388235,0.329412" Colorize="1">
            <Param index="HDRExposure" value="1.250000"/>
            <Param index="HDRBloomThreshold" value="0.275000"/>
            <Param index="HDRWhitePoint" value="1.850000"/>
            <Param index="HDRSpecMultiplier" value="0.750000"/>
            <Param index="HDREmisMultiplier" value="0.850000"/>
            <Param index="TerrainSpecularExp" value="10.000000"/>
            <Param index="TerrainHDRDiffuse" value="0.750000"/>
            <Param index="TerrainHDRSpecular" value="3.750000"/>
            <Param index="CreepHDRSpecMultiplier" value="8.040000"/>
            <Param index="ColorizationContrast" value="1.065000"/>
            <Param index="ColorizationHue" value="0.100000"/>
            <Param index="ColorizationSaturation" value="-0.504000"/>
            <Param index="ColorizationBlend" value="0.300000"/>
            <Param index="AONoOcclusion" value="5.876000"/>
            <DirectionalLight index="Key">
                <Color value="0.647059,0.776471,0.796078"/>
                <ColorMultiplier value="1.000000"/>
                <SpecColorMultiplier value="1.135000"/>
                <Direction value="0.624465,-0.021479,-0.780757"/>
            </DirectionalLight>
            <DirectionalLight index="Fill" Color="0.556863,0.541176,0.741176" ColorMultiplier="2.000000" Direction="-0.466126,-0.607907,0.642788"/>
            <DirectionalLight index="Back" Color="0.082353,0.125490,0.200000" ColorMultiplier="3.055000" Direction="-0.668793,-0.021251,0.743145"/>
        </ToDInfoArray>
    </CLight>
</Catalog>
