<?xml version="1.0" encoding="utf-8"?>
<Preload>
<Asset path="assets\textures\btn-tips-relicshrine.dds" Type="Image"/>
<Achievement id="Anniversary_TTychus02"/>
<Achievement id="TTychus02_1"/>
<Achievement id="TTychus02_2"/>
<Achievement id="TTychus02_3"/>
<Actor id="SYSTEM_ActorConfig"/>
<Actor id="PathingBlocker1x1Doodad"/>
<Actor id="PathingBlocker2x2Doodad"/>
<Actor id="BarracksWrecked"/>
<Actor id="Brambles" Variations="0,1,2,3,4,5,6,7"/>
<Actor id="BunkerWrecked"/>
<Actor id="CliffSpires" Variations="0,1"/>
<Actor id="CloudShadows"/>
<Actor id="ColonistShipAbandonedAngled" Variations="0"/>
<Actor id="CommandCenterWrecked"/>
<Actor id="DustStorms"/>
<Actor id="FlySwarm"/>
<Actor id="HavenUnderbrush" Variations="3"/>
<Actor id="MammothFossils" Variations="0,1,2,3"/>
<Actor id="MarSaraBones" Variations="3,4"/>
<Actor id="MarSaraSkeletonSmall" Variations="1"/>
<Actor id="Rock" Variations="0,1,2,3,4,5,6,7,8,9,10"/>
<Actor id="RockArch" Variations="7,9"/>
<Actor id="RockGiant" Variations="0,2,4,6,7,9,11,12,15,17"/>
<Actor id="RockLarge" Variations="0,3,4,7,9,10,11,12,13,16,17,18,19,20,21,22,23"/>
<Actor id="RockSmall" Variations="0,1,2,3,4,5,6,7,8,9,10"/>
<Actor id="SpacePlatformBarrier" Variations="0,1"/>
<Actor id="Spires" Variations="2,3"/>
<Actor id="TRaynor02CranePart3x3" Variations="1"/>
<Actor id="TRaynor02CranePart5x5" Variations="0,1,2"/>
<Actor id="WreckedBattlecruiser"/>
<Actor id="WreckedMule" Variations="0,1,2"/>
<Actor id="WreckedNomad"/>
<Actor id="WreckedSandbags" Variations="0,1"/>
<Actor id="WreckedVehicles" Variations="0"/>
<Actor id="XelNagaColumn"/>
<Actor id="XilFoliage" Variations="0,1,2,3,4,5"/>
<Actor id="XilFossils" Variations="0,1,6,7"/>
<Actor id="XilSpire" Variations="0,1,2,3,4"/>
<Actor id="XilSpireLarge" Variations="0,2,3,4"/>
<Actor id="XilTree" Variations="0,1,2,3,4,5,6,7"/>
<Actor id="ZhakulDasShrine" Variations="0,1,2"/>
<Actor id="ColonistSupplies" Variations="1,2,4,5,6,9"/>
<Actor id="ColonistSupplyCrate" Variations="0,2,4,5"/>
<Actor id="XelNagaTempleDirt"/>
<Actor id="LaserRegion"/>
<Actor id="ColonistCorpse" Variations="0,1,2,3,4,5,6,7,8,9,15"/>
<Model id="PingObjective"/>
<Model id="PingWarning"/>
<Model id="BriefingUnitSelect"/>
<Model id="BriefingUnitSelectLarge"/>
<Model id="XilSkybox"/>
<Model id="ArtifactPiece3"/>
<Sound id="Battlecruiser_YamatoAttackChargeUp"/>
<Sound id="UI_TerranPing"/>
<Sound id="UI_TerranReminderPing"/>
<Sound id="TUIWarningPing"/>
<Sound id="TTychus02BriefingAdjutant00001"/>
<Sound id="TTychus02BriefingTychus00002"/>
<Sound id="TTychus02BriefingTychus00003"/>
<Sound id="TTychus02BriefingRaynor00004"/>
<Sound id="TTychus02BriefingTychus00007"/>
<Sound id="TTychus02BriefingTychus00009"/>
<Sound id="TTychus02BriefingRaynor00011"/>
<Sound id="TTychus02TalDarimExecutor00001"/>
<Sound id="TTychus02Raynor00002"/>
<Sound id="TTychus02Raynor00003"/>
<Sound id="TTychus02Swann00004"/>
<Sound id="TTychus02Swann00005"/>
<Sound id="TTychus02Swann00006"/>
<Sound id="TTychus02Tychus00007"/>
<Sound id="TTychus02Tychus00008"/>
<Sound id="TTychus02Raynor00009"/>
<Sound id="TTychus02Tychus00010"/>
<Sound id="TTychus02Raynor00011"/>
<Sound id="TTychus02Raynor00012"/>
<Sound id="TTychus02Adjutant00013"/>
<Sound id="TTychus02Raynor00014"/>
<Sound id="TTychus02Raynor00015"/>
<Sound id="TTychus02Raynor00016"/>
<Sound id="TTychus02Raynor00018"/>
<Sound id="TTychus02Tychus00019"/>
<Sound id="TTychus02Raynor00020"/>
<Sound id="TTychus02Tychus00021"/>
<Sound id="TTychus02Adjutant00022"/>
<Sound id="TTychus02TalDarimExecutor00023"/>
<Sound id="TTychus02Adjutant00024"/>
<Sound id="TTychus02Adjutant00026"/>
<Sound id="TTychus02TalDarimExecutor00027"/>
<Sound id="TTychus02TalDarimExecutor00028"/>
<Sound id="TTychus02Adjutant00029"/>
<Sound id="TTychus02Raynor00030"/>
<Sound id="TTychus02Horner00031"/>
<Sound id="TTychus02Raynor00032"/>
<Sound id="TTychus02Horner00033"/>
<Sound id="TTychus02Raynor00034"/>
<Sound id="TTychus02Horner00035"/>
<Sound id="TTychus02Raynor00036"/>
<Sound id="TTychus02Horner00037"/>
<Sound id="TTychus02Horner00038"/>
<Sound id="TTychus02Horner00039"/>
<Sound id="TTychus02Adjutant00040"/>
<Sound id="TTychus02Raynor00041"/>
<Sound id="TTychus02Horner00042"/>
<Sound id="TTychus02Horner00043"/>
<Sound id="TTychus02Horner00044"/>
<Sound id="TTychus02Raynor00048"/>
<Sound id="TTychus02TalDarimExecutor00066"/>
<Sound id="TTychus02Raynor00067"/>
<Soundtrack id="TTychus02MusicAlt"/>
<Soundtrack id="TTychus02MusicIntro"/>
<Soundtrack id="TTychus02MusicMain"/>
<Soundtrack id="TTychus02MusicOutro"/>
<Terrain id="Xil"/>
<Unit id="Colossus"/>
<Unit id="CommandCenter"/>
<Unit id="SupplyDepot"/>
<Unit id="Refinery"/>
<Unit id="Barracks"/>
<Unit id="EngineeringBay"/>
<Unit id="MissileTurret"/>
<Unit id="Factory"/>
<Unit id="MercCompound"/>
<Unit id="SiegeTank"/>
<Unit id="FactoryTechLab"/>
<Unit id="SCV"/>
<Unit id="Marine"/>
<Unit id="Marauder"/>
<Unit id="Nexus"/>
<Unit id="Pylon"/>
<Unit id="Assimilator"/>
<Unit id="Gateway"/>
<Unit id="Forge"/>
<Unit id="FleetBeacon"/>
<Unit id="TwilightCouncil"/>
<Unit id="PhotonCannon"/>
<Unit id="Stargate"/>
<Unit id="TemplarArchive"/>
<Unit id="RoboticsBay"/>
<Unit id="RoboticsFacility"/>
<Unit id="CyberneticsCore"/>
<Unit id="Zealot"/>
<Unit id="Stalker"/>
<Unit id="HighTemplar"/>
<Unit id="Sentry"/>
<Unit id="Carrier"/>
<Unit id="VoidRay"/>
<Unit id="WarpPrism"/>
<Unit id="Observer"/>
<Unit id="Immortal"/>
<Unit id="Probe"/>
<Unit id="Archon"/>
<Unit id="CarrionBird"/>
<Unit id="MineralField" Variations="0,1,2,3,4,5,6,7,9"/>
<Unit id="VespeneGeyser"/>
<Unit id="PathingBlocker1x1"/>
<Unit id="Scout"/>
<Unit id="DrakkenLaserDrill"/>
<Unit id="SpecialOpsDropship"/>
<Unit id="XelNagaTemple"/>
<Unit id="SuperWarpGate"/>
<Unit id="XelNagaShrineXil"/>
<Unit id="ProtossRelic" Variations="2,4,6"/>
<Unit id="FlatbedTruck"/>
<Unit id="Food1000"/>
<Unit id="Medic"/>
</Preload>
