<?xml version="1.0" encoding="utf-8"?>
<Catalog>
    <CAttachMethodPattern id="AP_AMPatternDuskWingBanshee">
        <Keyword value="Weapon"/>
        <Driver value="AP_DuskWingBansheeLaunchMissile"/>
    </CAttachMethodPattern>
    <CAttachMethodPattern id="AP_AMPatternWreckingCrew">
        <Keyword value="Weapon"/>
        <Driver value="AP_WreckingCrewFighterLM"/>
    </CAttachMethodPattern>
    <CAttachMethodPattern id="AP_AMPatternSpartanCompany">
        <Keyword value="SetB"/>
        <Base value="::RollingIndex"/>
        <Multiplier value="2"/>
        <Driver value="AP_SpartanCompanyALM"/>
    </CAttachMethodPattern>
    <CAttachMethodFilter id="AP_AMFilterBattlecruiserHurricaneLeft">
        <Keys Keyword="Weapon" Index="20"/>
        <Keys Keyword="Weapon" Index="21"/>
        <Keys Keyword="Weapon" Index="25"/>
        <Logic value="OR"/>
    </CAttachMethodFilter>
    <CAttachMethodFilter id="AP_AMFilterBattlecruiserHurricaneRight">
        <Keys Keyword="Weapon" Index="22"/>
        <Keys Keyword="Weapon" Index="23"/>
        <Keys Keyword="Weapon" Index="24"/>
        <Logic value="OR"/>
    </CAttachMethodFilter>
    <CAttachMethodPattern id="AP_AMPatternGoliath">
        <Keyword value="SetB"/>
        <Base value="::RollingIndex"/>
        <Multiplier value="2"/>
        <Driver value="AP_GoliathALM"/>
    </CAttachMethodPattern>
    <CAttachMethodFilter id="AP_AMFilterDRCannons">
        <Logic value="OR"/>
        <Keys Keyword="Weapon" Index="10"/>
        <Keys Keyword="Weapon" Index="11"/>
    </CAttachMethodFilter>
    <CAttachMethodPattern id="AP_AMPatternDRCannonsG">
        <Keyword value="Weapon"/>
        <Base value="::RollingIndex"/>
        <Driver value="DRCannonsG"/>
    </CAttachMethodPattern>
    <CAttachMethodPattern id="AP_AMPatternDRCannonsA">
        <Keyword value="Weapon"/>
        <Base value="::RollingIndex"/>
        <Driver value="DRCannonsA"/>
    </CAttachMethodPattern>
    <CAttachMethodPattern id="AP_AMPatternDrunkenMissileVolley">
        <Keyword value="Weapon"/>
        <Driver value="AP_HailstormMissilePodsLaunchMissile"/>
    </CAttachMethodPattern>
</Catalog>
